slovene_accentuator/__init__.py
slovene_accentuator/accentuate.py
slovene_accentuator/get_models.py
slovene_accentuator/prepare_data.py
slovene_accentuator/data/environment.pkl
slovene_accentuator/data/mte_6_dict_sl_en.tsv
slovene_accentuator-0.0.10.dist-info/LICENSE
slovene_accentuator-0.0.10.dist-info/METADATA
slovene_accentuator-0.0.10.dist-info/WHEEL
slovene_accentuator-0.0.10.dist-info/top_level.txt
slovene_accentuator-0.0.10.dist-info/RECORD
